atsphinx/feed/__init__.py
atsphinx/feed/models.py
atsphinx/feed/processors.py
atsphinx_feed-0.1.2.dist-info/LICENSE
atsphinx_feed-0.1.2.dist-info/WHEEL
atsphinx_feed-0.1.2.dist-info/METADATA
atsphinx_feed-0.1.2.dist-info/RECORD
